MANIFEST.in
README.rst
setup.py
course/__init__.py
course/admin.py
course/apps.py
course/models.py
course/tests.py
course/views.py
django_huangwei_course.egg-info/PKG-INFO
django_huangwei_course.egg-info/SOURCES.txt
django_huangwei_course.egg-info/dependency_links.txt
django_huangwei_course.egg-info/requires.txt
django_huangwei_course.egg-info/top_level.txt