Metadata-Version: 1.0
Name: django-huangwei-course
Version: 0.1
Summary: A line of description
Home-page: UNKNOWN
Author: huangwei
Author-email: imonyse@gmail.com
License: MIT
Platform: UNKNOWN
